ipyvuetable/__init__.py
ipyvuetable/custom.css
ipyvuetable/editing_table.py
ipyvuetable/table.py
ipyvuetable/utils.py
ipyvuetable/widgets.py
ipyvuetable/filters/__init__.py
ipyvuetable/filters/filter.py
ipyvuetable/filters/filter_combo.py
ipyvuetable/filters/filter_date.py
ipyvuetable/filters/filter_datetime.py
ipyvuetable/filters/filter_slider.py
ipyvuetable-0.7.21.dist-info/METADATA
ipyvuetable-0.7.21.dist-info/WHEEL
ipyvuetable-0.7.21.dist-info/RECORD
