Metadata-Version: 2.4
Name: ipyvuetable
Version: 0.7.21
Summary: Table widget for Jupyter Notebook and JupyterLab
Project-URL: Homepage, https://github.com/gab23r/ipyvuetable
Author: Gabriel Robin
License: MIT
Requires-Python: >=3.10
Requires-Dist: ipyvuetify
Requires-Dist: polars
Provides-Extra: ipyevents
Requires-Dist: ipyevents; extra == 'ipyevents'
